privy/__init__.py
privy/_base_client.py
privy/_client.py
privy/_compat.py
privy/_constants.py
privy/_exceptions.py
privy/_files.py
privy/_models.py
privy/_qs.py
privy/_resource.py
privy/_response.py
privy/_streaming.py
privy/_types.py
privy/_version.py
privy/pagination.py
privy/py.typed
privy/_utils/__init__.py
privy/_utils/_logs.py
privy/_utils/_proxy.py
privy/_utils/_reflection.py
privy/_utils/_resources_proxy.py
privy/_utils/_streams.py
privy/_utils/_sync.py
privy/_utils/_transform.py
privy/_utils/_typing.py
privy/_utils/_utils.py
privy/lib/.keep
privy/lib/__init__.py
privy/lib/authorization_signatures.py
privy/lib/hpke.py
privy/lib/http_client.py
privy/lib/users.py
privy/lib/wallets.py
privy/lib/stablecoins/__init__.py
privy/lib/stablecoins/constants.py
privy/lib/stablecoins/erc20.py
privy/lib/stablecoins/usdc.py
privy/resources/__init__.py
privy/resources/key_quorums.py
privy/resources/policies.py
privy/resources/transactions.py
privy/resources/users.py
privy/resources/fiat/__init__.py
privy/resources/fiat/accounts.py
privy/resources/fiat/fiat.py
privy/resources/fiat/kyc.py
privy/resources/fiat/offramp.py
privy/resources/fiat/onramp.py
privy/resources/wallets/__init__.py
privy/resources/wallets/balance.py
privy/resources/wallets/transactions.py
privy/resources/wallets/wallets.py
privy/types/__init__.py
privy/types/fiat_configure_app_params.py
privy/types/fiat_configure_app_response.py
privy/types/fiat_get_kyc_link_params.py
privy/types/fiat_get_kyc_link_response.py
privy/types/fiat_get_status_params.py
privy/types/fiat_get_status_response.py
privy/types/key_quorum.py
privy/types/key_quorum_create_params.py
privy/types/key_quorum_update_params.py
privy/types/policy.py
privy/types/policy_create_params.py
privy/types/policy_update_params.py
privy/types/transaction_get_response.py
privy/types/user.py
privy/types/user_create_custom_metadata_response.py
privy/types/user_create_params.py
privy/types/user_delete_response.py
privy_client-0.4.0.dist-info/METADATA
privy_client-0.4.0.dist-info/WHEEL
privy_client-0.4.0.dist-info/licenses/LICENSE
privy_client-0.4.0.dist-info/RECORD
