Metadata-Version: 2.3
Name: privy-client
Version: 0.4.0
Summary: The official Python library for the Privy API
Project-URL: Homepage, https://github.com/privy-io/python-sdk
Project-URL: Repository, https://github.com/privy-io/python-sdk
Author-email: Privy API <support@privy.io>
License: Apache-2.0
Classifier: Intended Audience :: Developers
Classifier: License :: OSI Approved :: Apache Software License
Classifier: Operating System :: MacOS
Classifier: Operating System :: Microsoft :: Windows
Classifier: Operating System :: OS Independent
Classifier: Operating System :: POSIX
Classifier: Operating System :: POSIX :: Linux
Classifier: Programming Language :: Python :: 3.8
Classifier: Programming Language :: Python :: 3.9
Classifier: Programming Language :: Python :: 3.10
Classifier: Programming Language :: Python :: 3.11
Classifier: Programming Language :: Python :: 3.12
Classifier: Topic :: Software Development :: Libraries :: Python Modules
Classifier: Typing :: Typed
Requires-Python: >=3.8
Requires-Dist: anyio<5,>=3.5.0
Requires-Dist: cryptography>=44.0.3
Requires-Dist: distro<2,>=1.7.0
Requires-Dist: httpx<1,>=0.23.0
Requires-Dist: pydantic<3,>=1.9.0
Requires-Dist: pyhpke>=0.6.2
Requires-Dist: sniffio
Requires-Dist: typing-extensions<5,>=4.10
Requires-Dist: web3>=7.11.0
